[
    {
        "id":1,
        "SrcImage":["Home/kkr/kkr2012-1.jpg","Home/kkr/kkr2012-2.jpg","Home/kkr/kkr2012-3.jpg"],
        "alt":"KKR 2012 Trophy",
        "title": "KKR 2012 Trophy",
        "description":"The 2012 Indian Premier League final was a day/night Twenty20 cricket match on 27 May 2012 at the M. A. Chidambaram Stadium, Chennai, which was played between Chennai Super Kings and Kolkata Knight Riders to determine the winner of the 2012 season of the Indian Premier League, an annual Twenty20 cricket tournament in India.",
        "link":"https://youtu.be/6MlWdQoQN7s?si=5GaKd2MOKBuf2BMv",
        "more":"https://en.wikipedia.org/wiki/2012_Indian_Premier_League_final"
    },
    {
        "id":2,
        "SrcImage":["Home/kkr/kkr2014-1.jpg","Home/kkr/kkr2014-2.jpg","Home/kkr/kkr2014-3.jpg"],
        "alt":"KKR 2014 Trophy",
        "title": "KKR 2014 Trophy",
        "description":"Kolkata Knight Riders defeated Kings XI Punjab by 3 wickets to win the 2014 Indian Premier League in a high intensity final match, which was played in flawless spirit between the top two teams.",
        "link":"https://youtu.be/nPtIvA45Ju0?si=HYhAm4BzVDAycEtg",
        "more":"https://en.wikipedia.org/wiki/2014_Indian_Premier_League_final"
    }

]