[
    
{
    "id":74,
    "date":"Sun, 26 May",
    "team1":"SRH",
    "team1Logo":"Team/srhteam.png",
    "team1Score":"113 (20)",
    "team2":"KKR",
    "team2Logo":"Team/kkrteam.png",
    "team2Score":"114/2 (10.3)",
    "sortdesc":"KKR won by 8 wickets (57 balls left)",
    "highlights":"https://www.jiocinema.com/sports/cricket/final-kkr-vs-srh-highlights/3980221?utm_source=Onebox&utm_medium=GoogleHighlights&utm_campaign=Cricket_Highlights_TATA_IPL_2024_KKR_vs_SRH",
    "moreLink":"https://www.google.com/search?q=ipl+shedule&rlz=1C1UEAD_enIN1018IN1019&oq=ipl+sh&gs_lcrp=EgZjaHJvbWUqCAgAEEUYJxg7MggIABBFGCcYOzIGCAEQRRg5MgwIAhAAGBQYhwIYgAQyDAgDEAAYChixAxiABDIMCAQQABgKGLEDGIAEMgYIBRBFGDwyBggGEEUYPDIGCAcQRRg80gEIMTgyMGowajeoAgiwAgE&sourceid=chrome&ie=UTF-8#sie=m;/g/11vys0dg_g;5;/m/03b_lm1;dt;fp;1;;;",
    "imgSrc":"matches/srhVSkkr2.jpg",
    "winTeam":"team2",
    "duration":"15:00"
}
]